{"url": "https://www.securityweek.com/cylake-raises-45-million-to-secure-organizations-barred-from-cloud/", "original_lang": "en", "summary_vi": "Cylake Nhận 45 Triệu Đô La Đầu Tư Để Bảo Vệ Dữ Liệu Cho Các Tổ Chức Nghiêm Ngặt\n\nCybersecurity startup Cylake đã công bố ra mắt vào tuần trước, thu hút được 45 triệu đô la đầu tư hạt giống để phát triển một nền tảng được thiết kế dành riêng cho các tổ chức có quy định nghiêm ngặt và không thể sử dụng các dịch vụ đám mây công cộng.\n\nGreylock Partners dẫn đầu vòng đầu tư hạt giống này, sẽ cho phép Cylake hoàn thiện quá trình phát triển nền tảng dự kiến sẽ có sẵn rộng rãi vào đầu năm 2027.\n\nCylake được đồng sáng lập bởi Nir Zuk (CEO), Wilson Xu (chief development officer) và Ehud (Udi) Shamir (chief architect). Zuk là người sáng lập của Palo Alto Networks, từng giữ chức CTO của công ty trong hơn hai thập kỷ.\n\nShamir đồng sáng lập SentinelOne vào năm 2013 và cũng từng làm việc tại Palo Alto Networks với vai trò nhà phát triển phần mềm và nhà nghiên cứu bảo mật nổi bật. Xu từng giữ chức Phó chủ tịch kỹ thuật tại Palo Alto Networks trong hơn một thập kỷ. Họ còn được gia nhập bởi René Bonvanie, trước đây là Giám đốc Marketing của Palo Alto Networks.\n\nHiện tại, ít thông tin được công bố về nền tảng Cylake, nhưng công ty khẳng định nền tảng này được thiết kế để cung cấp khả năng bảo vệ dựa trên trí tuệ nhân tạo, tập trung vào quyền kiểm soát dữ liệu và vận hành.\n\nNền tảng này được quảng cáo là lý tưởng cho các công ty bị cấm sử dụng đám mây công cộng vì lý do bảo mật và quy định. Nền tảng Cylake được thiết kế để hoạt động hoàn toàn trên cơ sở trên địa bàn hoặc trong một đám mây riêng tư.\n\n“Nhiều nền tảng bảo mật hiện đại giả định rằng bạn có thể dựa vào cơ sở hạ tầng và dịch vụ đám mây để xử lý và phân tích dữ liệu bảo mật. Đám mây đã mang lại lợi ích thực sự cho những tiến bộ trong lĩnh vực an ninh mạng. Nhưng đối với một số tổ chức ngày nay, giả định đó không còn phù hợp nữa: quyền kiểm soát dữ liệu và kiểm soát vận hành là các yêu cầu, không phải là sở thích,” Nir Zuk giải thích.\n\n“Tình huống đó thay đổi mọi thứ. Bạn cần một hệ thống an ninh mạng dựa trên trí tuệ nhân tạo hoạt động quy mô lớn, trên toàn bộ dữ liệu, dưới sự kiểm soát của bạn và mà không thêm bất kỳ lớp phân mảnh nào,” Zuk tiếp thêm.\n\nLiên quan: ArmorCode Gõ Âm 16 Triệu Đô La Để Phát Triển Nền Tảng Quản Lý Tiếp Dẫn\n\nLiên quan: Công ty An ninh Dữ liệu Evervault Gõ Âm 25 Triệu Đô La Trong Giai Đoạn B\n\nLiên quan: Reclaim Security Gõ Âm 20 Triệu Đô La Để Tăng Tốc Quá Trình Khắc Phục", "audio_url": "/api/news/audio/6e8bd3d6e38b4bad5a7f478f751392e9.mp3", "hash": "6e8bd3d6e38b4bad5a7f478f751392e9"}